.DS_Store
notebooks/__init__.py
skelm/__init__.py
skelm/_version.py
skelm/elm.py
skelm/hidden_layer.py
skelm/large_elm.py
skelm/solver_batch.py
skelm/solver_dask.py
skelm/utils.py
skelm/tests/__init__.py
skelm/tests/test_acceptance.py
skelm/tests/test_acceptance_dask.py
skelm/tests/test_data.py
skelm/tests/test_features.py
skelm/tests/test_pandas.py
skelm/tests/test_projection.py
skelm/tests/test_serialization.py
skelm/tests/test_sklearn.py
skelm/tests/test_solvers.py
skelm/tests/test_unittests.py
scikit_elm-0.21a0.dist-info/LICENSE
scikit_elm-0.21a0.dist-info/METADATA
scikit_elm-0.21a0.dist-info/WHEEL
scikit_elm-0.21a0.dist-info/top_level.txt
scikit_elm-0.21a0.dist-info/RECORD
