Metadata-Version: 2.1
Name: scikit-elm
Version: 0.21a0
Summary: Extreme Learning Machine regressor/classifer compatible with scikit-learn
Home-page: https://github.com/akusok/scikit-elm
Maintainer: Anton Akusok
Maintainer-email: akusok.a@gmail.com
License: MIT
Download-URL: https://github.com/akusok/scikit-elm
Platform: UNKNOWN
Classifier: Intended Audience :: Science/Research
Classifier: Intended Audience :: Developers
Classifier: License :: OSI Approved
Classifier: Programming Language :: Python
Classifier: Topic :: Software Development
Classifier: Topic :: Scientific/Engineering
Classifier: Operating System :: Microsoft :: Windows
Classifier: Operating System :: POSIX
Classifier: Operating System :: Unix
Classifier: Operating System :: MacOS
Classifier: Programming Language :: Python :: 3.6
Classifier: Programming Language :: Python :: 3.7
Classifier: Programming Language :: Python :: 3.8
Provides-Extra: tests
Provides-Extra: docs
